deadnews_template_python/__init__.py
deadnews_template_python/__main__.py
deadnews_template_python/app.py
deadnews_template_python-2.1.0.dist-info/METADATA
deadnews_template_python-2.1.0.dist-info/WHEEL
deadnews_template_python-2.1.0.dist-info/entry_points.txt
deadnews_template_python-2.1.0.dist-info/licenses/LICENSE
deadnews_template_python-2.1.0.dist-info/RECORD
