Metadata-Version: 2.4
Name: deadnews-template-python
Version: 2.1.0
Summary: Python Project Template
Project-URL: Repository, https://github.com/deadnews/deadnews-template-python
Project-URL: Changelog, https://github.com/deadnews/deadnews-template-python/CHANGELOG.md
Project-URL: Documentation, https://deadnews.github.io/deadnews-template-python
Author-email: DeadNews <deadnewsgit@gmail.com>
License-Expression: MIT
License-File: LICENSE
Keywords: layout,python,template
Classifier: Operating System :: OS Independent
Requires-Python: >=3.13
Requires-Dist: fastapi[all]>=0.115.0
Requires-Dist: pydantic>=2.9.2
Requires-Dist: uvicorn>=0.34.0
